handystuff/__init__.py
handystuff/dispatch.py
handystuff/imports.py
handystuff/loaders.py
handystuff/logs.py
handystuff/prints.py
handystuff/registry.py
handystuff/stats.py
handystuff/resources/logging.jsonnet
tests/__init__.py
tests/test_main.py
handystuff-0.2.2.dist-info/METADATA
handystuff-0.2.2.dist-info/WHEEL
handystuff-0.2.2.dist-info/top_level.txt
handystuff-0.2.2.dist-info/RECORD
